physics_rs.cp312-win_amd64.pyd
physics/__init__.py
physics/_version.py
physics/environment.rs
physics/lib.rs
physics/models.rs
physics/environment/__init__.py
physics/environment/environment.rs
physics/environment/gis.rs
physics/environment/meteorology.rs
physics/environment/gis/__init__.py
physics/environment/gis/base_gis.py
physics/environment/gis/gis.py
physics/environment/gis/gis.rs
physics/environment/meteorology/__init__.py
physics/environment/meteorology/base_meteorology.py
physics/environment/meteorology/clouded_meteorology.py
physics/environment/meteorology/irradiant_meteorology.py
physics/environment/meteorology/meteorology.rs
physics/models/__init__.py
physics/models/arrays.rs
physics/models/battery.rs
physics/models/constants.py
physics/models/lvs.rs
physics/models/motor.rs
physics/models/regen.rs
physics/models/aeroshell/__init__.py
physics/models/aeroshell/aerodynamics.ipynb
physics/models/aeroshell/aeroshell.py
physics/models/aeroshell/drag_csv.csv
physics/models/arrays/__init__.py
physics/models/arrays/arrays.rs
physics/models/arrays/base_array.py
physics/models/arrays/basic_array.py
physics/models/battery/__init__.py
physics/models/battery/base_battery.py
physics/models/battery/basic_battery.py
physics/models/battery/battery.rs
physics/models/battery/battery_config.py
physics/models/battery/battery_config.toml
physics/models/battery/battery_model.py
physics/models/battery/kalman_filter.py
physics/models/lvs/__init__.py
physics/models/lvs/base_lvs.py
physics/models/lvs/basic_lvs.py
physics/models/lvs/lvs.rs
physics/models/motor/__init__.py
physics/models/motor/advanced_motor.py
physics/models/motor/base_motor.py
physics/models/motor/basic_motor.py
physics/models/motor/motor.rs
physics/models/regen/__init__.py
physics/models/regen/base_regen.py
physics/models/regen/basic_regen.py
physics/models/regen/regen.rs
physics_rs/__init__.pyi
ubc_solar_physics-1.9.1.dist-info/LICENSE
ubc_solar_physics-1.9.1.dist-info/METADATA
ubc_solar_physics-1.9.1.dist-info/WHEEL
ubc_solar_physics-1.9.1.dist-info/top_level.txt
ubc_solar_physics-1.9.1.dist-info/RECORD
