Metadata-Version: 2.1
Name: ubc-solar-physics
Version: 1.9.1
Summary: UBC Solar's Simulation Environment
Author: Fisher Xue, Mihir Nimgade, Chris Chang, David Widjaja, Justin Hua, Ilya Veksler, Renu Rajamagesh, Ritchie Xia, Erik Langille, Chris Aung, Nicolas Ric, Ishaan Trivedi, Jason Liang, Felix Toft, Mack Wilson, Jonah Lee, Tamzeed Quazi, Joshua Riefman
Author-email: UBC Solar <strategy@ubcsolar.com>
Maintainer: Renu Rajamagmesh, Felix Toft, Mack Wilson, Jonah Lee, Tamzeed Quazi
Maintainer-email: UBC Solar <strategy@ubcsolar.com>, Joshua Riefman <joshuariefman@gmail.com>
License: MIT License
Project-URL: Homepage, https://ubcsolar.com
Project-URL: Repository, https://github.com/UBC-Solar/physics
Project-URL: Documentation, https://ubc-solar-physics.readthedocs.io/en/latest/
Keywords: car,simulation,solar
Classifier: Programming Language :: Python :: 3
Classifier: Programming Language :: Rust
Classifier: Natural Language :: English
Classifier: Topic :: Scientific/Engineering :: Physics
Requires-Python: >=3.9
License-File: LICENSE
Requires-Dist: backports.tarfile ==1.2.0
Requires-Dist: certifi ==2024.7.4
Requires-Dist: charset-normalizer ==3.3.2
Requires-Dist: dill >=0.3.8
Requires-Dist: haversine ==2.8.1
Requires-Dist: idna ==3.7
Requires-Dist: importlib-metadata ==8.2.0
Requires-Dist: jaraco.classes ==3.4.0
Requires-Dist: jaraco.context ==5.3.0
Requires-Dist: jaraco.functools ==4.0.2
Requires-Dist: keyring ==25.3.0
Requires-Dist: llvmlite
Requires-Dist: markdown-it-py ==3.0.0
Requires-Dist: mdurl ==0.1.2
Requires-Dist: more-itertools ==10.4.0
Requires-Dist: nh3 ==0.2.18
Requires-Dist: numba
Requires-Dist: numpy >=2
Requires-Dist: pkginfo ==1.10.0
Requires-Dist: Pygments ==2.18.0
Requires-Dist: readme-renderer ==44.0
Requires-Dist: requests ==2.32.3
Requires-Dist: requests-toolbelt ==1.0.0
Requires-Dist: rfc3986 ==2.0.0
Requires-Dist: rich ==13.7.1
Requires-Dist: tqdm ==4.66.5
Requires-Dist: urllib3 ==2.2.2
Requires-Dist: zipp ==3.20.0
Requires-Dist: filterpy ==1.4.5
Requires-Dist: toml ==0.10.2
Requires-Dist: pandas
Requires-Dist: pydantic ==2.9.2
Requires-Dist: scipy
Requires-Dist: tomli
Requires-Dist: scipy-stubs
